{"metadata":{},"options":{"plugins":[{"key":"base$1$0","visitor":{"_exploded":{},"_verified":{},"JSXNamespacedName":{"enter":[null]},"JSXElement":{"exit":[null]},"JSXFragment":{"exit":[null]},"Program":{"enter":[null],"exit":[null]},"JSXAttribute":{"enter":[null]}},"options":{"pragma":"React.createElement","pragmaFrag":"React.Fragment","throwIfNamespace":true,"useBuiltIns":false}},{"key":"base$1$1","visitor":{"ExportDefaultDeclaration":{"enter":[null]},"CallExpression":{"enter":[null]},"_exploded":true,"_verified":true},"options":{}},{"key":"base$0$0","visitor":{"Program":{"enter":[null]},"_exploded":true,"_verified":true},"options":{"generateLetDeclarations":true,"enforceStrictMode":false}},{"key":"base$0$1","visitor":{"_exploded":true,"_verified":true},"options":{}},{"key":"base$0$2","visitor":{"_exploded":{},"_verified":{},"Program":{"enter":[null]},"ImportDeclaration":{"enter":[null,null]},"ClassProperty":{"enter":[null]},"ClassPrivateProperty":{"enter":[null]},"AssignmentPattern":{"enter":[null]},"TypeCastExpression":{"enter":[null,null]},"CallExpression":{"enter":[null]},"OptionalCallExpression":{"enter":[null]},"NewExpression":{"enter":[null]},"ImportSpecifier":{"enter":[null]},"ClassDeclaration":{"enter":[null]},"ClassExpression":{"enter":[null]},"FunctionDeclaration":{"enter":[null]},"FunctionExpression":{"enter":[null]},"ObjectMethod":{"enter":[null]},"ArrowFunctionExpression":{"enter":[null]},"ClassMethod":{"enter":[null]},"AnyTypeAnnotation":{"enter":[null]},"ArrayTypeAnnotation":{"enter":[null]},"BooleanTypeAnnotation":{"enter":[null]},"BooleanLiteralTypeAnnotation":{"enter":[null]},"NullLiteralTypeAnnotation":{"enter":[null]},"ClassImplements":{"enter":[null]},"DeclareClass":{"enter":[null]},"DeclareFunction":{"enter":[null]},"DeclareInterface":{"enter":[null]},"DeclareModule":{"enter":[null]},"DeclareModuleExports":{"enter":[null]},"DeclareTypeAlias":{"enter":[null]},"DeclareOpaqueType":{"enter":[null]},"DeclareVariable":{"enter":[null]},"DeclareExportDeclaration":{"enter":[null]},"DeclareExportAllDeclaration":{"enter":[null]},"DeclaredPredicate":{"enter":[null]},"ExistsTypeAnnotation":{"enter":[null]},"FunctionTypeAnnotation":{"enter":[null]},"FunctionTypeParam":{"enter":[null]},"GenericTypeAnnotation":{"enter":[null]},"InferredPredicate":{"enter":[null]},"InterfaceExtends":{"enter":[null]},"InterfaceDeclaration":{"enter":[null]},"InterfaceTypeAnnotation":{"enter":[null]},"IntersectionTypeAnnotation":{"enter":[null]},"MixedTypeAnnotation":{"enter":[null]},"EmptyTypeAnnotation":{"enter":[null]},"NullableTypeAnnotation":{"enter":[null]},"NumberLiteralTypeAnnotation":{"enter":[null]},"NumberTypeAnnotation":{"enter":[null]},"ObjectTypeAnnotation":{"enter":[null]},"ObjectTypeInternalSlot":{"enter":[null]},"ObjectTypeCallProperty":{"enter":[null]},"ObjectTypeIndexer":{"enter":[null]},"ObjectTypeProperty":{"enter":[null]},"ObjectTypeSpreadProperty":{"enter":[null]},"OpaqueType":{"enter":[null]},"QualifiedTypeIdentifier":{"enter":[null]},"StringLiteralTypeAnnotation":{"enter":[null]},"StringTypeAnnotation":{"enter":[null]},"ThisTypeAnnotation":{"enter":[null]},"TupleTypeAnnotation":{"enter":[null]},"TypeofTypeAnnotation":{"enter":[null]},"TypeAlias":{"enter":[null]},"TypeAnnotation":{"enter":[null]},"TypeParameter":{"enter":[null]},"TypeParameterDeclaration":{"enter":[null]},"TypeParameterInstantiation":{"enter":[null]},"UnionTypeAnnotation":{"enter":[null]},"Variance":{"enter":[null]},"VoidTypeAnnotation":{"enter":[null]},"ExportAllDeclaration":{"enter":[null]},"ExportDefaultDeclaration":{"enter":[null]},"ExportNamedDeclaration":{"enter":[null]}},"options":{}},{"key":"base$0$3","visitor":{"CallExpression":{"enter":[null]},"BinaryExpression":{"enter":[null]},"MemberExpression":{"enter":[null],"exit":[null]},"_exploded":true,"_verified":true,"Identifier":{"enter":[null]},"JSXIdentifier":{"enter":[null]}},"options":{}},{"key":"base$0$4","visitor":{"_exploded":true,"_verified":true},"options":{}},{"key":"base$0$5","visitor":{"_exploded":{},"_verified":{},"VariableDeclarator":{"enter":[null]},"ExportNamedDeclaration":{"enter":[null]},"CatchClause":{"enter":[null]},"AssignmentExpression":{"enter":[null]},"ObjectExpression":{"enter":[null]},"FunctionDeclaration":{"enter":[null]},"FunctionExpression":{"enter":[null]},"ObjectMethod":{"enter":[null]},"ArrowFunctionExpression":{"enter":[null]},"ClassMethod":{"enter":[null]},"ForInStatement":{"enter":[null]},"ForOfStatement":{"enter":[null]}},"options":{}},{"key":"transform-meteor-async-await","visitor":{"AwaitExpression":{"enter":[null]},"_exploded":true,"_verified":true,"FunctionDeclaration":{"exit":[null]},"FunctionExpression":{"exit":[null]},"ObjectMethod":{"exit":[null]},"ArrowFunctionExpression":{"exit":[null]},"ClassMethod":{"exit":[null]}},"options":{"useNativeAsyncAwait":false}},{"key":"transform-meteor-dynamic-import","visitor":{"_exploded":{},"_verified":{},"CallExpression":{"enter":[null]}},"options":{}},{"key":"base$0$8","visitor":{"_exploded":{},"_verified":{},"Program":{"enter":[null]}},"options":{}},{"key":"base$0$9","visitor":{"Program":{"exit":[null]},"_exploded":true,"_verified":true},"options":{"allowTopLevelThis":true,"strictMode":false,"loose":true}},{"key":"base$0$10","visitor":{"_exploded":{},"_verified":{},"PrivateName":{"enter":[null]},"ClassDeclaration":{"enter":[null]},"ClassExpression":{"enter":[null]}},"options":{"loose":true}}],"compact":false,"sourceMaps":true,"ast":true,"babelrc":false,"configFile":false,"parserOpts":{"sourceType":"module","sourceFileName":"/Users/gongxuecrise/Documents/GitHub/manoaclubroom/app/imports/api/stuff/stuff.js","plugins":["*","flow","jsx","asyncGenerators","bigInt","classPrivateMethods","classPrivateProperties","classProperties","doExpressions","dynamicImport","exportDefaultFrom","exportExtensions","exportNamespaceFrom","functionBind","functionSent","importMeta","nullishCoalescingOperator","numericSeparator","objectRestSpread","optionalCatchBinding","optionalChaining",["pipelineOperator",{"proposal":"minimal"}],"throwExpressions","jsx",["flow",{}],["flow",{}],"objectRestSpread","objectRestSpread","dynamicImport","asyncGenerators","classProperties","classPrivateProperties"],"allowImportExportEverywhere":true,"allowReturnOutsideFunction":true,"strictMode":false},"caller":{"name":"meteor","arch":"os.osx.x86_64"},"sourceFileName":"imports/api/stuff/stuff.js","filename":"/Users/gongxuecrise/Documents/GitHub/manoaclubroom/app/imports/api/stuff/stuff.js","passPerPreset":false,"envName":"development","cwd":"/Users/gongxuecrise/Documents/GitHub/manoaclubroom/app","root":"/Users/gongxuecrise/Documents/GitHub/manoaclubroom/app","presets":[],"generatorOpts":{"filename":"/Users/gongxuecrise/Documents/GitHub/manoaclubroom/app/imports/api/stuff/stuff.js","comments":true,"compact":false,"sourceMaps":true,"sourceFileName":"imports/api/stuff/stuff.js"}},"code":"module.export({\n  Stuffs: () => Stuffs,\n  StuffSchema: () => StuffSchema\n});\nlet Mongo;\nmodule.link(\"meteor/mongo\", {\n  Mongo(v) {\n    Mongo = v;\n  }\n\n}, 0);\nlet SimpleSchema;\nmodule.link(\"simpl-schema\", {\n  default(v) {\n    SimpleSchema = v;\n  }\n\n}, 1);\nlet Tracker;\nmodule.link(\"meteor/tracker\", {\n  Tracker(v) {\n    Tracker = v;\n  }\n\n}, 2);\n\n/** Create a Meteor collection. */\nconst Stuffs = new Mongo.Collection('Stuffs');\n/** Create a schema to constrain the structure of documents associated with this collection. */\n\nconst StuffSchema = new SimpleSchema({\n  name: String,\n  location: String,\n  time: String,\n  interest: String,\n  image: String,\n  description: String\n}, {\n  tracker: Tracker\n});\n/** Attach this schema to the collection. */\n\nStuffs.attachSchema(StuffSchema);\n/** Make the collection and schema available to other code. */","map":{"version":3,"sources":["imports/api/stuff/stuff.js"],"names":["module","export","Stuffs","StuffSchema","Mongo","link","v","SimpleSchema","default","Tracker","Collection","name","String","location","time","interest","image","description","tracker","attachSchema"],"mappings":"AAAAA,MAAM,CAACC,MAAP,CAAc;AAACC,EAAAA,MAAM,EAAC,MAAIA,MAAZ;AAAmBC,EAAAA,WAAW,EAAC,MAAIA;AAAnC,CAAd;AAA+D,IAAIC,KAAJ;AAAUJ,MAAM,CAACK,IAAP,CAAY,cAAZ,EAA2B;AAACD,EAAAA,KAAK,CAACE,CAAD,EAAG;AAACF,IAAAA,KAAK,GAACE,CAAN;AAAQ;;AAAlB,CAA3B,EAA+C,CAA/C;AAAkD,IAAIC,YAAJ;AAAiBP,MAAM,CAACK,IAAP,CAAY,cAAZ,EAA2B;AAACG,EAAAA,OAAO,CAACF,CAAD,EAAG;AAACC,IAAAA,YAAY,GAACD,CAAb;AAAe;;AAA3B,CAA3B,EAAwD,CAAxD;AAA2D,IAAIG,OAAJ;AAAYT,MAAM,CAACK,IAAP,CAAY,gBAAZ,EAA6B;AAACI,EAAAA,OAAO,CAACH,CAAD,EAAG;AAACG,IAAAA,OAAO,GAACH,CAAR;AAAU;;AAAtB,CAA7B,EAAqD,CAArD;;AAInN;AACA,MAAMJ,MAAM,GAAG,IAAIE,KAAK,CAACM,UAAV,CAAqB,QAArB,CAAf;AAEA;;AACA,MAAMP,WAAW,GAAG,IAAII,YAAJ,CAAiB;AACnCI,EAAAA,IAAI,EAAEC,MAD6B;AAEnCC,EAAAA,QAAQ,EAAED,MAFyB;AAGnCE,EAAAA,IAAI,EAAEF,MAH6B;AAInCG,EAAAA,QAAQ,EAAEH,MAJyB;AAKnCI,EAAAA,KAAK,EAAEJ,MAL4B;AAMnCK,EAAAA,WAAW,EAAEL;AANsB,CAAjB,EAOjB;AAAEM,EAAAA,OAAO,EAAET;AAAX,CAPiB,CAApB;AASA;;AACAP,MAAM,CAACiB,YAAP,CAAoBhB,WAApB;AAEA","sourcesContent":["import { Mongo } from 'meteor/mongo';\nimport SimpleSchema from 'simpl-schema';\nimport { Tracker } from 'meteor/tracker';\n\n/** Create a Meteor collection. */\nconst Stuffs = new Mongo.Collection('Stuffs');\n\n/** Create a schema to constrain the structure of documents associated with this collection. */\nconst StuffSchema = new SimpleSchema({\n  name: String,\n  location: String,\n  time: String,\n  interest: String,\n  image: String,\n  description: String,\n}, { tracker: Tracker });\n\n/** Attach this schema to the collection. */\nStuffs.attachSchema(StuffSchema);\n\n/** Make the collection and schema available to other code. */\nexport { Stuffs, StuffSchema };\n"]},"sourceType":"script","hash":"750da028b1a213a20b7714f9bbe80b3190d44990"}
